MANIFEST.in
README.md
requirements.txt
requirements_core.txt
setup.py
bin/set-deploy-status
deploy_agent.egg-info/PKG-INFO
deploy_agent.egg-info/SOURCES.txt
deploy_agent.egg-info/dependency_links.txt
deploy_agent.egg-info/entry_points.txt
deploy_agent.egg-info/requires.txt
deploy_agent.egg-info/top_level.txt
deployd/__init__.py
deployd/agent.py
deployd/client/__init__.py
deployd/client/base_client.py
deployd/client/client.py
deployd/client/restfulclient.py
deployd/client/serverless_client.py
deployd/common/__init__.py
deployd/common/caller.py
deployd/common/config.py
deployd/common/decorators.py
deployd/common/env_status.py
deployd/common/exceptions.py
deployd/common/executor.py
deployd/common/helper.py
deployd/common/single_instance.py
deployd/common/stats.py
deployd/common/status_code.py
deployd/common/types.py
deployd/common/utils.py
deployd/conf/__init__.py
deployd/conf/agent.conf
deployd/download/__init__.py
deployd/download/download_helper.py
deployd/download/download_helper_factory.py
deployd/download/downloader.py
deployd/download/gpg_helper.py
deployd/download/http_download_helper.py
deployd/download/local_download_helper.py
deployd/download/s3_download_helper.py
deployd/staging/__init__.py
deployd/staging/stager.py
deployd/staging/transformer.py
deployd/types/__init__.py
deployd/types/agent_status.py
deployd/types/build.py
deployd/types/deploy_goal.py
deployd/types/deploy_stage.py
deployd/types/deploy_type.py
deployd/types/opcode.py
deployd/types/ping_report.py
deployd/types/ping_request.py
deployd/types/ping_response.py