Metadata-Version: 1.0
Name: deploy-agent
Version: 1.2.17
Summary: UNKNOWN
Home-page: UNKNOWN
Author: Pinterest
Author-email: UNKNOWN
License: UNKNOWN
Platform: UNKNOWN
